huobi_client
