Metadata-Version: 1.0
Name: huobi-client
Version: 0.3.0
Summary: a client library for huobi
Home-page: UNKNOWN
Author: czheo
Author-email: UNKNOWN
License: LGPL
Keywords: bitcoin huobi huobi.com
Platform: UNKNOWN
